PyNonpar/__init__.py
PyNonpar/hettmansperger.py
PyNonpar/multisample.py
PyNonpar/pseudorank.py
PyNonpar/repeated_measures.py
PyNonpar/twosample.py
PyNonpar/twosample_paired.py
PyNonpar-0.2.0.dist-info/METADATA
PyNonpar-0.2.0.dist-info/RECORD
PyNonpar-0.2.0.dist-info/WHEEL
PyNonpar-0.2.0.dist-info/top_level.txt
