Metadata-Version: 2.1
Name: PyNonpar
Version: 0.2.0
Summary: Nonparametric Test Statistics
Home-page: https://github.com/happma/PyNonpar
Author: Martin Happ
Author-email: martin.happ@aon.at
License: GPL-3
Platform: UNKNOWN
Classifier: Development Status :: 2 - Pre-Alpha
Classifier: Programming Language :: Python :: 3.7
Classifier: Programming Language :: Python :: 3.6
Classifier: License :: OSI Approved :: GNU General Public License v3 (GPLv3)
Classifier: Operating System :: OS Independent
Classifier: Topic :: Scientific/Engineering :: Mathematics
Classifier: Topic :: Software Development :: Libraries :: Python Modules
Classifier: Environment :: Console
Classifier: Intended Audience :: End Users/Desktop
Classifier: Intended Audience :: Developers
Classifier: Intended Audience :: Science/Research
Requires-Dist: numpy
Requires-Dist: pandas
Requires-Dist: pytest
Requires-Dist: scipy
Requires-Dist: pytest-cov
Requires-Dist: codecov
Requires-Dist: numba
